mtpiclick/__init__.py
mtpiclick/click.py
mtpiclick/point.py
mtpiclick/cseries/__init__.py
mtpiclick/cseries/xga/__init__.py
mtpiclick/cseries/xga/coordinates.py
mtpiclick/cseries/xga/hmi.py
mtpiclick/cseries/xga/keyboard.py
mtpiclick/cseries/xga/login.py
mtpiclick/cseries/xga/supervisor.py
mtpiclick-0.0.7.dist-info/LICENSE
mtpiclick-0.0.7.dist-info/METADATA
mtpiclick-0.0.7.dist-info/WHEEL
mtpiclick-0.0.7.dist-info/top_level.txt
mtpiclick-0.0.7.dist-info/RECORD
