Metadata-Version: 2.1
Name: mtpiclick
Version: 0.0.7
Summary: HMI automation tools.
Home-page: UNKNOWN
Author: Patrick Toohey
License: UNKNOWN
Platform: UNKNOWN
Requires-Python: >=3.7
License-File: LICENSE
Requires-Dist: pyautogui
Requires-Dist: pywinauto
